README.md
config.ini
main.py
requirements.txt
tokenManager.json
how2validate/__init__.py
how2validate/validator.py
how2validate/handler/email_handler.py
how2validate/handler/validator_handler.py
how2validate/utility/config_utility.py
how2validate/utility/log_utility.py
how2validate/utility/token_utility.py
how2validate/utility/tool_utility.py
how2validate/utility/interface/EmailResponse.py
how2validate/utility/interface/secretStatusMessage.py
how2validate/utility/interface/validationResult.py
how2validate/validators/adafruit/adafruit_io_key.py
how2validate/validators/aiven/aiven_auth_token.py
how2validate/validators/anthropic/anthropic_api_key.py
how2validate/validators/discord/discord_bot_token.py
how2validate/validators/github/github_personal_access_token.py
how2validate/validators/hugging_face/hf_org_api_key.py
how2validate/validators/hugging_face/hf_user_access_token.py
how2validate/validators/npm/npm_access_token.py
how2validate/validators/openai/openai_api_key.py
how2validate/validators/pagerduty/pagerduty_api_key.py
how2validate/validators/sentry/sentry_auth_token.py
how2validate/validators/slack/slack_api_token.py
how2validate/validators/snyk/snyk_auth_key.py
how2validate/validators/sonarcloud/sonarcloud_token.py
tests/__init__.py
tests/validator_test.py
how2validate-0.1.6.dist-info/METADATA
how2validate-0.1.6.dist-info/WHEEL
how2validate-0.1.6.dist-info/entry_points.txt
how2validate-0.1.6.dist-info/top_level.txt
how2validate-0.1.6.dist-info/RECORD
