Metadata-Version: 2.4
Name: how2validate
Version: 0.1.6
Summary: A CLI tool to validate secrets for different services.
Home-page: https://github.com/Blackplums/how2validate
Author: Vigneshkna
Author-email: vigneshkna@gmail.com
License: MIT
Requires-Dist: certifi==2025.8.3
Requires-Dist: cffi==2.0.0
Requires-Dist: charset-normalizer==3.4.3
Requires-Dist: cryptography==46.0.1
Requires-Dist: dnspython==2.8.0
Requires-Dist: docutils==0.22.2
Requires-Dist: id==1.5.0
Requires-Dist: idna==3.10
Requires-Dist: jaraco-classes==3.4.0
Requires-Dist: jaraco-context==6.0.1
Requires-Dist: jaraco-functools==4.3.0
Requires-Dist: jeepney==0.9.0
Requires-Dist: keyring==25.6.0
Requires-Dist: markdown-it-py==4.0.0
Requires-Dist: mdurl==0.1.2
Requires-Dist: more-itertools==10.8.0
Requires-Dist: nh3==0.3.0
Requires-Dist: packaging==25.0
Requires-Dist: pycparser==2.23
Requires-Dist: pygments==2.19.2
Requires-Dist: pymongo==4.15.1
Requires-Dist: pyopenssl==25.3.0
Requires-Dist: python-dotenv==1.1.1
Requires-Dist: readme-renderer==44.0
Requires-Dist: requests==2.32.5
Requires-Dist: requests-toolbelt==1.0.0
Requires-Dist: rfc3986==2.0.0
Requires-Dist: rich==14.1.0
Requires-Dist: secretstorage==3.4.0
Requires-Dist: semver==3.0.4
Requires-Dist: tabulate==0.9.0
Requires-Dist: twine==6.2.0
Requires-Dist: typing-extensions==4.15.0
Requires-Dist: urllib3==2.5.0
Requires-Dist: wheel==0.45.1
Dynamic: author
Dynamic: author-email
Dynamic: description
Dynamic: description-content-type
Dynamic: home-page
Dynamic: license
Dynamic: requires-dist
Dynamic: summary
